pandas_missing/Missing.py
pandas_missing/__init__.py
pandas_missing/_modidx.py
pandas_missing/basic_numerical_summaries.py
pandas_missing/basic_summaries.py
pandas_missing-0.0.12.dist-info/LICENSE
pandas_missing-0.0.12.dist-info/METADATA
pandas_missing-0.0.12.dist-info/WHEEL
pandas_missing-0.0.12.dist-info/entry_points.txt
pandas_missing-0.0.12.dist-info/top_level.txt
pandas_missing-0.0.12.dist-info/RECORD
