Metadata-Version: 2.1
Name: pandas-missing
Version: 0.0.12
Summary: A pandas extension to explore and handling missing values.
Home-page: https://github.com/jvelezmagic/pandas-missing/
Author: Jesús Vélez Santiago
Author-email: jvelezmagic@gmail.com
License: Apache Software License 2.0
Keywords: nbdev pandas missing-values handling-missing-values
Classifier: Development Status :: 3 - Alpha
Classifier: Intended Audience :: Developers
Classifier: Natural Language :: English
Classifier: Programming Language :: Python :: 3.9
Classifier: Programming Language :: Python :: 3.10
Classifier: License :: OSI Approved :: Apache Software License
Requires-Python: >=3.9
License-File: LICENSE
Requires-Dist: fastcore
Requires-Dist: pandas
Requires-Dist: matplotlib
Requires-Dist: seaborn
Requires-Dist: missingno
Provides-Extra: dev
Requires-Dist: jupyter ; extra == 'dev'
Requires-Dist: black ; extra == 'dev'
Requires-Dist: nbdev ; extra == 'dev'
